hypofuzz/__init__.py
hypofuzz/bayes.py
hypofuzz/build.py
hypofuzz/collection.py
hypofuzz/compat.py
hypofuzz/corpus.py
hypofuzz/coverage.py
hypofuzz/detection.py
hypofuzz/entrypoint.py
hypofuzz/hypofuzz.py
hypofuzz/mutator.py
hypofuzz/provider.py
hypofuzz/py.typed
hypofuzz/utils.py
hypofuzz/dashboard/api.py
hypofuzz/dashboard/dashboard.py
hypofuzz/dashboard/models.py
hypofuzz/dashboard/patching.py
hypofuzz/dashboard/test.py
hypofuzz/dashboard/websocket.py
hypofuzz/database/__init__.py
hypofuzz/database/database.py
hypofuzz/database/models.py
hypofuzz/database/utils.py
hypofuzz/docs/changelog.md
hypofuzz/docs/cli_output_fuzz.txt
hypofuzz/docs/compatibility.rst
hypofuzz/docs/conf.py
hypofuzz/docs/features.rst
hypofuzz/docs/index.rst
hypofuzz/docs/literature.bib
hypofuzz/docs/literature.rst
hypofuzz/docs/prolog.rst
hypofuzz/docs/quickstart.rst
hypofuzz/docs/redirect.html.template
hypofuzz/docs/reference.rst
hypofuzz/docs/_ext/hypothesis_redirects.py
hypofuzz/docs/_ext/__pycache__/hypothesis_redirects.cpython-311.pyc
hypofuzz/docs/_static/no-scroll.css
hypofuzz/docs/manual/behavior.rst
hypofuzz/docs/manual/cli.rst
hypofuzz/docs/manual/collection.rst
hypofuzz/docs/manual/database.rst
hypofuzz/docs/manual/index.rst
hypofuzz/docs/manual/operating.rst
hypofuzz/frontend/eslint.config.mjs
hypofuzz/frontend/index.html
hypofuzz/frontend/package-lock.json
hypofuzz/frontend/package.json
hypofuzz/frontend/tsconfig.json
hypofuzz/frontend/tsconfig.node.json
hypofuzz/frontend/vite.config.ts
hypofuzz/frontend/dist/index.html
hypofuzz/frontend/dist/assets/d3-DfGPKUIz.js
hypofuzz/frontend/dist/assets/d3-DfGPKUIz.js.map
hypofuzz/frontend/dist/assets/index-BgxNR_s6.js
hypofuzz/frontend/dist/assets/index-BgxNR_s6.js.map
hypofuzz/frontend/dist/assets/index-DhPn2tMx.css
hypofuzz/frontend/dist/assets/jsonWorker-KJVNTzbb.js
hypofuzz/frontend/dist/assets/jsonWorker-KJVNTzbb.js.map
hypofuzz/frontend/dist/assets/react-jY7NyK-3.js
hypofuzz/frontend/dist/assets/react-jY7NyK-3.js.map
hypofuzz-25.11.1.dist-info/licenses/CONTRIBUTING.md
hypofuzz-25.11.1.dist-info/licenses/LICENSE
hypofuzz-25.11.1.dist-info/METADATA
hypofuzz-25.11.1.dist-info/WHEEL
hypofuzz-25.11.1.dist-info/entry_points.txt
hypofuzz-25.11.1.dist-info/top_level.txt
hypofuzz-25.11.1.dist-info/RECORD
