Metadata-Version: 2.4
Name: hypofuzz
Version: 25.11.1
Summary: Adaptive fuzzing for property-based tests
Author-email: Zac Hatfield-Dodds <zac@hypofuzz.com>
License-Expression: LicenseRef-HypoFuzz
Project-URL: homepage, https://hypofuzz.com/
Project-URL: source, https://github.com/Zac-HD/hypofuzz
Project-URL: documentation, https://hypofuzz.com/docs/
Project-URL: changelog, https://hypofuzz.com/docs/changelog.html
Keywords: python,testing,fuzzing,property-based-testing
Classifier: Development Status :: 5 - Production/Stable
Classifier: Framework :: Hypothesis
Classifier: Intended Audience :: Developers
Classifier: Programming Language :: Python
Classifier: Programming Language :: Python :: 3
Classifier: Programming Language :: Python :: 3.10
Classifier: Programming Language :: Python :: 3.11
Classifier: Programming Language :: Python :: 3.12
Classifier: Programming Language :: Python :: 3.13
Classifier: Programming Language :: Python :: 3.14
Classifier: Topic :: Software Development :: Testing
Requires-Python: >=3.10
License-File: LICENSE
License-File: CONTRIBUTING.md
Requires-Dist: black>=23.3.0
Requires-Dist: coverage>=5.2.1
Requires-Dist: hypothesis[cli,watchdog]>=6.140.2
Requires-Dist: libcst>=1.0.0
Requires-Dist: psutil>=3.0.0
Requires-Dist: pytest>=7.0.0
Requires-Dist: starlette
Requires-Dist: trio
Requires-Dist: hypercorn
Dynamic: license-file
